pip_services4_messaging/__init__.py
pip_services4_messaging/build/DefaultMessagingFactory.py
pip_services4_messaging/build/IMessageQueueFactory.py
pip_services4_messaging/build/MemoryMessageQueueFactory.py
pip_services4_messaging/build/MessageQueueFactory.py
pip_services4_messaging/build/__init__.py
pip_services4_messaging/connect/IMessageQueueConnection.py
pip_services4_messaging/connect/__init__.py
pip_services4_messaging/queues/CachedMessageQueue.py
pip_services4_messaging/queues/CallbackMessageReceiver.py
pip_services4_messaging/queues/IMessageQueue.py
pip_services4_messaging/queues/IMessageReceiver.py
pip_services4_messaging/queues/LockedMessage.py
pip_services4_messaging/queues/MemoryMessageQueue.py
pip_services4_messaging/queues/MessageEnvelope.py
pip_services4_messaging/queues/MessageQueue.py
pip_services4_messaging/queues/MessagingCapabilities.py
pip_services4_messaging/queues/__init__.py
pip_services4_messaging/test/TestMessageReceiver.py
pip_services4_messaging/test/__init__.py
pip_services4_messaging-0.0.1.dist-info/LICENSE
pip_services4_messaging-0.0.1.dist-info/METADATA
pip_services4_messaging-0.0.1.dist-info/WHEEL
pip_services4_messaging-0.0.1.dist-info/top_level.txt
pip_services4_messaging-0.0.1.dist-info/zip-safe
pip_services4_messaging-0.0.1.dist-info/RECORD
